redact_pdf/__init__.py
redact_pdf/redact.py
redact_pdf-0.0.3.dist-info/LICENSE
redact_pdf-0.0.3.dist-info/METADATA
redact_pdf-0.0.3.dist-info/WHEEL
redact_pdf-0.0.3.dist-info/RECORD
