Metadata-Version: 2.1
Name: redact_pdf
Version: 0.0.3
Summary: redact a phrase off a pdf file
Home-page: https://github.com/levyvix/redact-pdf
Author: Levy Nunes
Author-email: levy.vix@gmail.com
Requires-Python: >=3.9,<4.0
Classifier: Programming Language :: Python :: 3
Classifier: Programming Language :: Python :: 3.9
Classifier: Programming Language :: Python :: 3.10
Classifier: Programming Language :: Python :: 3.11
Classifier: Programming Language :: Python :: 3.12
Requires-Dist: loguru (>=0.7.2,<0.8.0)
Requires-Dist: pymupdf (>=1.24.14,<2.0.0)
Project-URL: Documentation, https://levyvix.github.io/redact-pdf/
Project-URL: Repository, https://github.com/levyvix/redact-pdf
